datupapi/__init__.py
datupapi/configure/__init__.py
datupapi/configure/config.py
datupapi/distribution/conf/__init__.py
datupapi/distribution/src/DistributionFunctions/__init__.py
datupapi/distribution/src/DistributionFunctions/functions_distribution.py
datupapi/distribution/src/Format/__init__.py
datupapi/distribution/src/Format/distribution_format.py
datupapi/evaluate/__init__.py
datupapi/evaluate/anomaly.py
datupapi/evaluate/errors.py
datupapi/extract/__init__.py
datupapi/extract/io.py
datupapi/extract/io_citrix.py
datupapi/extract/io_opt.py
datupapi/feateng/__init__.py
datupapi/feateng/relation.py
datupapi/feateng/scale.py
datupapi/inventory/conf/__init__.py
datupapi/inventory/src/DailyUsage/__init__.py
datupapi/inventory/src/DailyUsage/daily_usage.py
datupapi/inventory/src/Format/__init__.py
datupapi/inventory/src/Format/inventory_format.py
datupapi/inventory/src/FutureInventory/__init__.py
datupapi/inventory/src/FutureInventory/daily_usage_future.py
datupapi/inventory/src/FutureInventory/future_reorder.py
datupapi/inventory/src/InventoryFunctions/__init__.py
datupapi/inventory/src/InventoryFunctions/functions_inventory.py
datupapi/inventory/src/ProcessForecast/__init__.py
datupapi/inventory/src/ProcessForecast/define_periods.py
datupapi/inventory/src/ProcessForecast/extract_forecast.py
datupapi/inventory/src/SuggestedForecast/__init__.py
datupapi/inventory/src/SuggestedForecast/suggested_forecast.py
datupapi/inventory/src/Transformation/__init__.py
datupapi/inventory/src/Transformation/inventory_transformation.py
datupapi/predict/__init__.py
datupapi/predict/forecast.py
datupapi/prepare/__init__.py
datupapi/prepare/cleanse.py
datupapi/prepare/format.py
datupapi/prepare/format_dask.py
datupapi/prepare/format_opt.py
datupapi/training/__init__.py
datupapi/training/attup.py
datupapi/training/deepar.py
datupapi/training/tft.py
datupapi/transform/__init__.py
datupapi/transform/backtesting.py
datupapi/transform/forecasting.py
datupapi/transform/ranking.py
datupapi-1.115.0.dist-info/METADATA
datupapi-1.115.0.dist-info/WHEEL
datupapi-1.115.0.dist-info/top_level.txt
datupapi-1.115.0.dist-info/RECORD
