Metadata-Version: 2.4
Name: datupapi
Version: 1.115.0
Summary: Utility library to support Datup AI MLOps processes
Author: Datup AI
Author-email: ramiro@datup.ai
Requires-Dist: s3fs<2026.0.0,>=2024.6.1
Requires-Dist: aiobotocore[boto3]<3.0.0,>=2.5.4
Requires-Dist: boto3<2.0.0,>=1.33.13
Requires-Dist: botocore<2.0.0,>=1.33.13
Requires-Dist: beautifulsoup4>=4.9.3
Requires-Dist: catboost>=1.0.4
Requires-Dist: datetime>=4.3
Requires-Dist: google-cloud-bigquery>=2.34.2
Requires-Dist: google-cloud-storage>=2.1.0
Requires-Dist: hdbcli>=2.17.22
Requires-Dist: lxml>=4.9.2
Requires-Dist: mysql-connector-python>=8.0.24
Requires-Dist: numpy>=2.0.0
Requires-Dist: openpyxl>=3.0.6
Requires-Dist: pandas>=2.2.2
Requires-Dist: pulp>=2.7.0
Requires-Dist: pyarrow>=10.0.1
Requires-Dist: pymssql>=2.2.7
Requires-Dist: pymysql>=1.0.2
Requires-Dist: pyod>=2.0.2
Requires-Dist: pytest>=6.2.1
Requires-Dist: python-dateutil>=2.8.2
Requires-Dist: pyyaml>=5.3.1
Requires-Dist: requests>=2.25.1
Requires-Dist: scikit-learn>=0.24.1
Requires-Dist: shap>=0.40.0
Requires-Dist: SQLAlchemy>=1.3.22
Requires-Dist: sqlalchemy-hana>=0.5.0
Requires-Dist: unidecode>=1.1.2
Requires-Dist: xlrd>=1.0.0
Requires-Dist: fuzzywuzzy>=0.18.0
Requires-Dist: statsmodels>=0.13.2
Provides-Extra: dev
Requires-Dist: pytest>=6.2.1; extra == "dev"
Dynamic: author
Dynamic: author-email
Dynamic: description
Dynamic: description-content-type
Dynamic: provides-extra
Dynamic: requires-dist
Dynamic: summary
